{
  "name": "YouTube Vocabulary - saXs-rRFTpM",
  "language": "apc",
  "tasks": [
    {
      "language": "apc",
      "content": "Watch & try to understand the video <https://www.youtube.com/watch?v=saXs-rRFTpM>",
      "primaryUnitsOfMeaning": [
        {
          "language": "apc",
          "content": "ابو",
          "translations": [
            {
              "language": "eng",
              "content": "father"
            }
          ]
        },
        {
          "language": "apc",
          "content": "علي",
          "translations": [
            {
              "language": "eng",
              "content": "Ali"
            }
          ]
        },
        {
          "language": "apc",
          "content": "بيزعل",
          "translations": [
            {
              "language": "eng",
              "content": "gets upset"
            }
          ]
        },
        {
          "language": "apc",
          "content": "بلا",
          "translations": [
            {
              "language": "eng",
              "content": "without"
            }
          ]
        },
        {
          "language": "apc",
          "content": "ما",
          "translations": [
            {
              "language": "eng",
              "content": "not"
            }
          ]
        },
        {
          "language": "apc",
          "content": "هون",
          "translations": [
            {
              "language": "eng",
              "content": "here"
            }
          ]
        },
        {
          "language": "apc",
          "content": "بدي",
          "translations": [
            {
              "language": "eng",
              "content": "I want"
            }
          ]
        },
        {
          "language": "apc",
          "content": "خلص",
          "translations": [
            {
              "language": "eng",
              "content": "finished"
            }
          ]
        },
        {
          "language": "apc",
          "content": "شو",
          "translations": [
            {
              "language": "eng",
              "content": "what"
            }
          ]
        },
        {
          "language": "apc",
          "content": "بدك",
          "translations": [
            {
              "language": "eng",
              "content": "do you want"
            }
          ]
        },
        {
          "language": "apc",
          "content": "فيه",
          "translations": [
            {
              "language": "eng",
              "content": "in it"
            }
          ]
        },
        {
          "language": "apc",
          "content": "رايح",
          "translations": [
            {
              "language": "eng",
              "content": "going"
            }
          ]
        },
        {
          "language": "apc",
          "content": "وجاي",
          "translations": [
            {
              "language": "eng",
              "content": "and coming"
            }
          ]
        },
        {
          "language": "apc",
          "content": "اوكي",
          "translations": [
            {
              "language": "eng",
              "content": "Okay"
            }
          ]
        },
        {
          "language": "apc",
          "content": "اهلا",
          "translations": [
            {
              "language": "eng",
              "content": "Hello"
            }
          ]
        },
        {
          "language": "apc",
          "content": "سهلا",
          "translations": [
            {
              "language": "eng",
              "content": "Welcome"
            }
          ]
        },
        {
          "language": "apc",
          "content": "نورت",
          "translations": [
            {
              "language": "eng",
              "content": "You enlightened"
            }
          ]
        },
        {
          "language": "apc",
          "content": "وشرفت",
          "translations": [
            {
              "language": "eng",
              "content": "You honored"
            }
          ]
        },
        {
          "language": "apc",
          "content": "انا",
          "translations": [
            {
              "language": "eng",
              "content": "I"
            }
          ]
        },
        {
          "language": "apc",
          "content": "بس",
          "translations": [
            {
              "language": "eng",
              "content": "Just"
            }
          ]
        },
        {
          "language": "apc",
          "content": "قالوا",
          "translations": [
            {
              "language": "eng",
              "content": "They said"
            }
          ]
        },
        {
          "language": "apc",
          "content": "لي",
          "translations": [
            {
              "language": "eng",
              "content": "to me"
            }
          ]
        },
        {
          "language": "apc",
          "content": "انك",
          "translations": [
            {
              "language": "eng",
              "content": "that you"
            }
          ]
        },
        {
          "language": "apc",
          "content": "جيت",
          "translations": [
            {
              "language": "eng",
              "content": "you came"
            }
          ]
        },
        {
          "language": "apc",
          "content": "نزلت",
          "translations": [
            {
              "language": "eng",
              "content": "you went down"
            }
          ]
        },
        {
          "language": "apc",
          "content": "ركت",
          "translations": [
            {
              "language": "eng",
              "content": "you parked"
            }
          ]
        },
        {
          "language": "apc",
          "content": "يا",
          "translations": [
            {
              "language": "eng",
              "content": "O"
            }
          ]
        },
        {
          "language": "apc",
          "content": "كبير",
          "translations": [
            {
              "language": "eng",
              "content": "big"
            }
          ]
        },
        {
          "language": "apc",
          "content": "احلى",
          "translations": [
            {
              "language": "eng",
              "content": "better"
            },
            {
              "language": "eng",
              "content": "most beautiful"
            }
          ]
        },
        {
          "language": "apc",
          "content": "برجر",
          "translations": [
            {
              "language": "eng",
              "content": "burger"
            }
          ]
        },
        {
          "language": "apc",
          "content": "وصلك",
          "translations": [
            {
              "language": "eng",
              "content": "brought to you"
            }
          ]
        },
        {
          "language": "apc",
          "content": "اياها",
          "translations": [
            {
              "language": "eng",
              "content": "it"
            }
          ]
        },
        {
          "language": "apc",
          "content": "من",
          "translations": [
            {
              "language": "eng",
              "content": "from"
            }
          ]
        },
        {
          "language": "apc",
          "content": "تحت",
          "translations": [
            {
              "language": "eng",
              "content": "under"
            }
          ]
        },
        {
          "language": "apc",
          "content": "ايدي",
          "translations": [
            {
              "language": "eng",
              "content": "my hand"
            }
          ]
        },
        {
          "language": "apc",
          "content": "قاللك",
          "translations": [
            {
              "language": "eng",
              "content": "he said to you"
            }
          ]
        },
        {
          "language": "apc",
          "content": "بيع",
          "translations": [
            {
              "language": "eng",
              "content": "sale"
            }
          ]
        },
        {
          "language": "apc",
          "content": "قال",
          "translations": [
            {
              "language": "eng",
              "content": "said"
            }
          ]
        },
        {
          "language": "apc",
          "content": "بقوللك",
          "translations": [
            {
              "language": "eng",
              "content": "I tell you"
            }
          ]
        },
        {
          "language": "apc",
          "content": "هلا",
          "translations": [
            {
              "language": "eng",
              "content": "now"
            }
          ]
        },
        {
          "language": "apc",
          "content": "قسما",
          "translations": [
            {
              "language": "eng",
              "content": "I swear"
            }
          ]
        },
        {
          "language": "apc",
          "content": "بالله",
          "translations": [
            {
              "language": "eng",
              "content": "by God"
            }
          ]
        },
        {
          "language": "apc",
          "content": "خص",
          "translations": [
            {
              "language": "eng",
              "content": "specific"
            }
          ]
        },
        {
          "language": "apc",
          "content": "قاللي",
          "translations": [
            {
              "language": "eng",
              "content": "he told me"
            }
          ]
        },
        {
          "language": "apc",
          "content": "اص",
          "translations": [
            {
              "language": "eng",
              "content": "father"
            }
          ]
        }
      ],
      "secondaryUnitsOfMeaning": [],
      "lastDownloadedAt": null,
      "lastPracticedAt": null,
      "isCompleted": false,
      "nextShownEarliestAt": "2024-01-01T00:00:00.000Z",
      "interval": 0,
      "attempts": []
    }
  ]
}